markdown_normalization-0.0.4.dist-info/METADATA
markdown_normalization-0.0.4.dist-info/WHEEL
markdown_normalization/__init__.py
markdown_normalization/markdown_normalization.cpython-310-darwin.so
markdown_normalization/markdown_normalization.pyi
markdown_normalization/py.typed
markdown_normalization-0.0.4.dist-info/RECORD
