Metadata-Version: 2.4
Name: markdown_normalization
Version: 0.0.4
Classifier: Programming Language :: Python :: 3
Classifier: Programming Language :: Rust
Classifier: License :: OSI Approved :: MIT License
Classifier: Operating System :: OS Independent
Requires-Dist: maturin>=1.9.3
Summary: Fast Markdown codeblock and URL normalization in Rust
Author-email: Oscar Bahamonde <oscar.bahamonde@pucp.pe>
License-Expression: MIT
Requires-Python: >=3.8
